tuft/__init__.py
tuft/__main__.py
tuft/auth.py
tuft/backend.py
tuft/checkpoints.py
tuft/cli.py
tuft/config.py
tuft/exceptions.py
tuft/futures.py
tuft/sampling_controller.py
tuft/server.py
tuft/state.py
tuft/training_controller.py
tuft/backends/__init__.py
tuft/backends/base_backend.py
tuft/backends/hf_training_model.py
tuft/backends/sampling_backend.py
tuft/backends/training_backend.py
tuft/loss_fn/__init__.py
tuft/loss_fn/cispo.py
tuft/loss_fn/cross_entropy.py
tuft/loss_fn/dro.py
tuft/loss_fn/importance_sampling.py
tuft/loss_fn/ppo.py
tuft/persistence/__init__.py
tuft/persistence/file_redis.py
tuft/persistence/redis_store.py
tuft/telemetry/__init__.py
tuft/telemetry/metrics.py
tuft/telemetry/provider.py
tuft/telemetry/tracing.py
tuft-0.1.2.dist-info/METADATA
tuft-0.1.2.dist-info/WHEEL
tuft-0.1.2.dist-info/entry_points.txt
tuft-0.1.2.dist-info/licenses/LICENSE
tuft-0.1.2.dist-info/RECORD
