Metadata-Version: 2.4
Name: tuft
Version: 0.1.2
Summary: A multi-tenant fine-tuning platform for LLMs with Tinker-compatible API
Author-email: TuFT Developers <tuft@list.alibaba-inc.com>
License: MIT License
License-File: LICENSE
Requires-Python: >=3.11
Requires-Dist: fastapi>=0.125.0
Requires-Dist: httpx>=0.28.1
Requires-Dist: numpy<2.0.0
Requires-Dist: nvidia-ml-py>=13.0.0
Requires-Dist: omegaconf>=2.3.0
Requires-Dist: opentelemetry-api>=1.20.0
Requires-Dist: opentelemetry-exporter-otlp>=1.20.0
Requires-Dist: opentelemetry-instrumentation-fastapi>=0.41b0
Requires-Dist: opentelemetry-instrumentation-logging>=0.41b0
Requires-Dist: opentelemetry-sdk>=1.20.0
Requires-Dist: psutil>=5.9.0
Requires-Dist: ray>=2.50.0
Requires-Dist: tinker>=0.7.0
Requires-Dist: transformers<5.0.0,>=4.57.3
Requires-Dist: typer>=0.20.1
Requires-Dist: uvicorn[standard]>=0.38.0
Provides-Extra: backend
Requires-Dist: datasets>=4.0.0; extra == 'backend'
Requires-Dist: huggingface-hub<1.0,>=0.20.0; extra == 'backend'
Requires-Dist: peft>=0.18.0; extra == 'backend'
Requires-Dist: trinity-rft[vllm]>=0.4.1; extra == 'backend'
Provides-Extra: dev
Requires-Dist: detect-secrets>=1.5.0; extra == 'dev'
Requires-Dist: nbqa>=1.9.1; extra == 'dev'
Requires-Dist: pre-commit>=4.5.1; extra == 'dev'
Requires-Dist: pyright>=1.1.408; extra == 'dev'
Requires-Dist: pytest-asyncio>=1.3.0; extra == 'dev'
Requires-Dist: pytest-json-ctrf; extra == 'dev'
Requires-Dist: pytest>=9.0.2; extra == 'dev'
Requires-Dist: ruff>=0.14.14; extra == 'dev'
Provides-Extra: persistence
Requires-Dist: redis>=5.0.0; extra == 'persistence'
